ccplot/__init__.py
ccplot/algorithms.cp313-win_amd64.pyd
ccplot/algorithms.pyx
ccplot/autostr.py
ccplot/cctk.c
ccplot/cctk.cp313-win_amd64.pyd
ccplot/config.py
ccplot/hdf.cp313-win_amd64.pyd
ccplot/hdf.dll
ccplot/hdf.pyx
ccplot/hdfeos.cp313-win_amd64.pyd
ccplot/hdfeos.pyx
ccplot/mfhdf.dll
ccplot/utils.py
ccplot/xdr.dll
ccplot/bin/__init__.py
ccplot/bin/ccplot.py
ccplot-2.1.5.data/data/share/ccplot/cmap/calipso-backscatter.cmap
ccplot-2.1.5.data/data/share/ccplot/cmap/calipso-cratio.cmap
ccplot-2.1.5.data/data/share/ccplot/cmap/calipso-dratio.cmap
ccplot-2.1.5.data/data/share/ccplot/cmap/calipso-temperature.cmap
ccplot-2.1.5.data/data/share/ccplot/cmap/cloudsat-reflectivity.cmap
ccplot-2.1.5.data/data/share/ccplot/cmap/modis-reflectance.cmap
ccplot-2.1.5.data/data/share/ccplot/cmap/modis-temperature.cmap
ccplot-2.1.5.data/data/share/doc/ccplot/NEWS
ccplot-2.1.5.data/data/share/man/man1/ccplot.1
ccplot-2.1.5.dist-info/LICENSE
ccplot-2.1.5.dist-info/METADATA
ccplot-2.1.5.dist-info/WHEEL
ccplot-2.1.5.dist-info/entry_points.txt
ccplot-2.1.5.dist-info/top_level.txt
ccplot-2.1.5.dist-info/RECORD
