Metadata-Version: 2.1
Name: ccplot
Version: 2.1.5
Summary: CloudSat and CALIPSO plotting tool
Home-page: http://www.ccplot.org/
Author: Peter Kuma
Author-email: peter@peterkuma.net
License: BSD
Platform: any
Classifier: Development Status :: 5 - Production/Stable
Classifier: Environment :: Console
Classifier: Intended Audience :: Science/Research
Classifier: License :: OSI Approved :: BSD License
Classifier: Natural Language :: English
Classifier: Operating System :: MacOS :: MacOS X
Classifier: Operating System :: Microsoft :: Windows
Classifier: Operating System :: POSIX
Classifier: Programming Language :: C
Classifier: Programming Language :: Cython
Classifier: Programming Language :: Python :: 3
Classifier: Topic :: Scientific/Engineering :: Atmospheric Science
Classifier: Topic :: Scientific/Engineering :: Visualization
Requires-Python: >=3.0.0
License-File: LICENSE
Requires-Dist: numpy<2.0.0,>=1.1
Requires-Dist: matplotlib>=0.98.1
Requires-Dist: cartopy>=0.17.0
Requires-Dist: packaging>=20.03
Requires-Dist: pytz
